{
  "description": "",
  "displayName": "Timeline",
  "methods": [],
  "props": {
    "align": {
      "type": {
        "name": "enum",
        "value": [
          {
            "value": "'alternate'",
            "computed": false
          },
          {
            "value": "'left'",
            "computed": false
          },
          {
            "value": "'right'",
            "computed": false
          }
        ]
      },
      "required": false,
      "description": "The position where the timeline's content should appear.",
      "defaultValue": {
        "value": "'left'",
        "computed": false
      },
      "tags": []
    },
    "children": {
      "type": {
        "name": "node"
      },
      "required": false,
      "description": "The content of the component.",
      "tags": []
    },
    "classes": {
      "type": {
        "name": "object"
      },
      "required": false,
      "description": "Override or extend the styles applied to the component.\r\nSee [CSS API](#css) below for more details.",
      "tags": []
    }
  },
  "name": "Timeline",
  "styles": {
    "classes": [
      "root",
      "alignLeft",
      "alignRight",
      "alignAlternate"
    ],
    "name": "MuiTimeline",
    "descriptions": {
      "root": "Styles applied to the root element.",
      "alignLeft": "Styles applied to the root element if `align=\"left\"`.",
      "alignRight": "Styles applied to the root element if `align=\"right\"`.",
      "alignAlternate": "Styles applied to the root element if `align=\"alternate\"`."
    },
    "globalClasses": {
      "root": "MuiTimeline-root",
      "alignLeft": "MuiTimeline-alignLeft",
      "alignRight": "MuiTimeline-alignRight",
      "alignAlternate": "MuiTimeline-alignAlternate"
    }
  },
  "spread": true,
  "forwardsRefTo": "HTMLUListElement",
  "filename": "\\packages\\material-ui-lab\\src\\Timeline\\Timeline.js",
  "inheritance": null,
  "usedInPages": [
    "/components/timeline"
  ]
}
